computer_architecture/cache_verilog/Cache.v
/*H**********************************************************************
* FILENAME :        Cache.v            
*
* DESCRIPTION :
*       Module definition for Direct Mapped Cache. The Cache has a total size
*       of 32 bytes, consisting of 8 cache blocks with 4 bytes per block.
*
* MICRO ARCHITECTURE :
*       The Cache module implements a finite state machine with 4 states. The initial
*       state is the IDLE state where the component is waiting for a MR command. 
*
*       Once a command is received, it is recorded as either WRITE or READ. The internal
*       state transitions to the TEST state where we test for a cache hit. Once the test is 
*       completed, the system transitions to the R_FETCH or W_FETCH according to the input command.\
*
*       If a READ command was placed, the system transitions to the R_FETCH state. If we have a cache hit,
*       the request memory word is returned from cache. Otherwise, in the case of a miss, the requested
*       address and it's associated memory block is fetched, cached, and the requested word is returned.
*
*       If a WRITE command was placed, the system transitions to the W_FETCH state. If we have cache hit, 
*       the corresponding word in the cache is written to in addition to the associated word in memory. Otherwise,
*       cache misses are handled by only updating the associated word in memory.
*
* AUTHOR :    Yousef Yassin        START DATE :     8 Oct 21
*H*/

`define PURPLE(x) `"\033[35m[x]\033[0m`"

/* Cache FSM States */
`define IDLE 3'd0
`define TEST 3'd1
`define R_FETCH 3'd2
`define R_FETCH_RST 3'd3
`define R_READY 3'd4
`define W_FETCH 3'd5
`define W_FETCH_RST 3'd6
`define W_DONE 3'd7

/* Input Command Type */
`define READ 1'b0
`define WRITE 1'b1

module Cache
(
    // Standard Synchronous Signals
    input clk,
    input rst,

    // Interface Processor
    input PRead_request, PWrite_request,
    input[7:0] PWrite_data, PAddress,
    output[7:0] PRead_data,
    output PRead_ready, PWrite_done,

    //Interface Memory
    output MRead_request, MWrite_request,
    output[7:0] MWrite_data, MAddress,
    input[31:0] MRead_data,
    input MRead_ready, MWrite_done
);

/*
    Cache and memory blocks consist of 4 bytes.
    8-bit memory address spaces => 256 total words, 64 blocks
    Cache is 32 bytes => 8 blocks

    4 bytes / block => 2-bit offset (o)
    8 cache blocks => 3-bit index (i)
    tag is remainder => 3-bit tag, makes sense since (t)
    8 memory blocks map to each cache block.

    Address Format: 0b tttiiioo
*/

/*
    8 blocks, each with 4 bytes.
    Indexed: cache[block][byte][bit]
*/

reg[7:0] cache[0:7][0:3]; 
reg[2:0] tags[0:7];     // Eight 3-bit tags, for each cache block
reg valid[0:7];         // Tracks invalid data at init

reg[2:0] state;         // Internal state
// Design Choice: avoids repetitives states R_xx and W_xx.
reg command;            // Input command type
reg hit;                // 1 if cache hit, else 0
reg[7:0] read_buf;      // Temporary data

/* Split input PAddress into tag, index and offset bits */
wire[2:0] tag;
wire[2:0] block_index;
wire[1:0] offset;
assign tag = PAddress[7:5];
assign block_index = PAddress[4:2];
assign offset = PAddress[1:0];

/* Initialization, Cache Reset */
integer i, j; // Loop vars
always@(posedge clk) begin
    if (rst) begin
        state <= `IDLE;
        command <= `READ;
        read_buf <= 8'd0;

        // Initialize reg arrays to 0
        for (i = 0; i < 8; i = i + 1) begin
            tags[i] <= 3'b000;
            valid[i] <= 1'b0;
            for (j = 0; j < 4; j = j + 1) cache[i][j] <= 8'd0;
        end
    end
end

/* Main - Cache State Machine */
always@(posedge clk) begin
    case (state) 
        `IDLE: begin
            if (PRead_request || PWrite_request) begin
                command = PRead_request ? `READ : `WRITE; 
                state <= `TEST;
            end 
            else begin
                state <= `IDLE;
            end
        end

        `TEST: begin
            // We can skip some states if we hit on a read
            if ((tag == tags[block_index] && valid[block_index]) && ~command) begin
                $display("%s Read cache hit @ 0b%b", `PURPLE(META), PAddress);
                read_buf <= cache[block_index][offset];
                state <= `R_READY;
            end
            else begin
                hit <= (tag == tags[block_index] && valid[block_index]);
                state <= command ? `W_FETCH : `R_FETCH;
            end
        end

        `R_FETCH: begin
            if (MRead_ready) begin
                $display("%s Read cache missed @ 0b%b", `PURPLE(META), PAddress);
                // Litte Endian
                cache[block_index][0] <= MRead_data[7:0];
                cache[block_index][1] <= MRead_data[15:8];
                cache[block_index][2] <= MRead_data[23:16];
                cache[block_index][3] <= MRead_data[31:24];

                tags[block_index] <= tag;
                valid[block_index] <= 1'b1;

                state <= `R_FETCH_RST;
            end
        end

        `R_FETCH_RST: begin
            read_buf <= cache[block_index][offset];
            state <= `R_READY;
        end

        `R_READY: begin
            // Return to idle once processor ack
            if (~PRead_request) begin
                state <= `IDLE;
            end
            else begin
                state <= `R_READY;
            end
        end

        `W_FETCH: begin
            if (MWrite_done) begin
                // Write back: Update memory and cache
                if (hit) begin
                    $display("%s Write cache hit @ 0b%b", `PURPLE(META), PAddress);
                    cache[block_index][offset] <= PWrite_data;
                end
                else begin
                    $display("%s Write cache missed @ 0b%b", `PURPLE(META), PAddress);
                end
                state <= `W_FETCH_RST;
            end 
            else begin
                state <= `W_FETCH;
            end
        end

        `W_FETCH_RST: begin
            state <= `W_DONE;
        end

        `W_DONE: begin
            // Return to idle once processor ack
            if (~PWrite_request) begin
                state <= `IDLE;
            end
            else begin
                state <= `W_DONE;
            end
        end
    endcase
end

// Cache miss, fetch associated block and return word
// Fetch from block base, so mask off offsets.
assign MAddress = (state == `R_FETCH) ? PAddress & 8'b11111100 : 
                  (state == `W_FETCH) ? PAddress : 
                  8'd0; 
 
assign MRead_request = (state == `R_FETCH);
assign MWrite_request = (state == `W_FETCH);
assign PRead_ready = (state == `R_READY);
assign PWrite_done = (state == `W_DONE);
assign PRead_data = read_buf;
assign MWrite_data = PWrite_data;
endmodule

computer_architecture/cache_verilog/Cache_tb.v
`timescale 1ns / 1ns
`include "Cache.v"

`define GREEN(x) `"\033[32m\x\033[0m`"
`define CYAN(x) `"\033[36m[x]\033[0m`"
`define RED(x) `"\033[31m[x]\033[0m`"
`define YELLOW(x) `"\033[33m[x]\033[0m`"

module Cache_tb;

    /* Testing IO setup */
    reg Clk, Rst, PR_req, PW_req, MR_rdy, MW_done;
    reg[7:0] PW_data, PAddr;
    reg[31:0]MR_data;
    wire PR_rdy, PW_done, MR_req, MW_req;
    wire[7:0] PR_data, MW_data, MAddr;

    // 64 word memory bank for testing, 16 blocks
    reg[7:0] memory[0:63];

    Cache dut
    (
        // Synchronous Logic Inputs
        .clk(Clk),
        .rst(Rst),

        // IProcessor
        .PRead_request(PR_req),
        .PWrite_request(PW_req),
        .PWrite_data(PW_data),
        .PRead_data(PR_data),
        .PRead_ready(PR_rdy),
        .PWrite_done(PW_done),
        .PAddress(PAddr),

        // IMemory
        .MRead_request(MR_req),
        .MWrite_request(MW_req),
        .MWrite_data(MW_data),
        .MRead_data(MR_data),
        .MRead_ready(MR_rdy),
        .MWrite_done(MW_done), 
        .MAddress(MAddr)
    );

    integer i; // Memory init loop index var
    initial begin
        /* Waveform Setup */
        $dumpfile("Cache_tb.vcd");
        $dumpvars(0, Cache_tb);

        /* --- Initialization Reset --- */
        // Set all memory words to 0
        for (i = 0; i < 64; i = i + 1) memory[i] = i; //$urandom%255

        // Reset inputs
        PR_req = 1'b0;
        PW_req = 1'b0;
        MR_rdy = 1'b0;
        MW_done = 1'b0;
        PW_data = 8'd0;
        PAddr = 8'd0;
        MR_data = 32'd0;

        Clk = 1'b0;
        Rst = 1'b1;
        #5;
        
        /* --- Test Cases --- */
        @(posedge Clk);
        Rst = 1'b0;
        #10;

        /** Read miss
            Description: Should result in a cache miss at 0b101,
            fetch from 0b100 and return the memory.
        */
        $display("\n%s", `GREEN(Read request miss @ 0b101));
        @(posedge Clk);
        PAddr = 8'b00000101;    // Fetch 0b00000101
        PR_req = 1'b1;          // Won't hit, should fetch from mem @ [4]
        #1;
        
        @(posedge MR_req);
        @(posedge Clk);
        $display("%s Memory read request @0b%b", `YELLOW(INFO) ,MAddr);
        MR_data = { memory[MAddr + 8'd3], memory[MAddr + 8'd2], memory[MAddr + 8'd1], memory[MAddr] };
        MR_rdy = 1'b1;
        #1;

        @(posedge PR_rdy);
        @(posedge Clk);
        MR_rdy = 1'b0;
        $display("%s Cache returned: 0b%b, should be: 0b%b.", `CYAN(PASS), PR_data, memory[PAddr]);
        #1;
        @(posedge Clk);
        PR_req = 1'b0; // ack
        #1;

        /** Read miss
            Description: Should result in a cache miss at 0b101,
            fetch from 0b100 and return the memory.
        */
        $display("\n%s", `GREEN(Read request miss @ 0b11));
        @(posedge Clk);
        PAddr = 8'b00000011;    // Fetch @0b00000011
        PR_req = 1'b1;          // Won't hit, should fetch from mem @ [0]
        #1;
        
        @(posedge MR_req);
        @(posedge Clk);
        $display("%s Memory read request @0b%b", `YELLOW(INFO) ,MAddr);
        MR_data = { memory[MAddr + 8'd3], memory[MAddr + 8'd2], memory[MAddr + 8'd1], memory[MAddr] };
        MR_rdy = 1'b1;
        #1;

        @(posedge PR_rdy);
        @(posedge Clk);
        MR_rdy = 1'b0;
        $display("%s Cache returned: 0b%b, should be: 0b%b.", `CYAN(PASS), PR_data, memory[PAddr]);
        #1;
        @(posedge Clk);
        PR_req = 1'b0; // ack
        #1;

        /** Read hit
            Description: Should result in a cache hit at 0b111, 
            and return the memory.
        */
        $display("\n%s", `GREEN(Read request hit @ 0b111));
        @(posedge Clk);
        PAddr = 8'b00000111;    // Fetch @0b00000111 
        PR_req = 1'b1;          // should hit
        #1;

        @(posedge PR_rdy);
        @(posedge Clk);
        $display("%s Cache returned: 0b%b, should be: 0b%b.", `CYAN(PASS), PR_data, memory[PAddr]);
        #1;
        @(posedge Clk);
        PR_req = 1'b0; // ack
        #1;

        /** Read hit
            Description: Should result in a cache hit at 0b1, 
            and return the memory.
        */
        $display("\n%s", `GREEN(Read request hit @ 0b1));
        @(posedge Clk);
        PAddr = 8'b00000001;    // Fetch @0b0000001
        PR_req = 1'b1;          // should hit
        #1;

        @(posedge PR_rdy);
        @(posedge Clk);
        $display("%s Cache returned: %b, should be: %b.", `CYAN(PASS), PR_data, memory[PAddr]);
        #1;
        @(posedge Clk);
        PR_req = 1'b0; // ack
        #1;

        /** Read miss
            Description: Should result in a cache miss at 0b100110 (38).
            This maps to block 1 (starting with 36) and should trash.
        */
        $display("\n%s", `GREEN(Read request miss @ 0b100110));
        @(posedge Clk);
        PAddr = 8'b00100110;    // Fetch @0b00100110
        PR_req = 1'b1;          // Won't hit, should fetch from mem @ [36]
        #1;
        
        @(posedge MR_req);
        @(posedge Clk);
        $display("%s Memory read request @0b%b", `YELLOW(INFO), MAddr);
        MR_data = { memory[MAddr + 8'd3], memory[MAddr + 8'd2], memory[MAddr + 8'd1], memory[MAddr] };
        MR_rdy = 1'b1;
        #1;

        @(posedge PR_rdy);
        @(posedge Clk);
        MR_rdy = 1'b0;
        $display("%s Cache returned: %b, should be: %b.", `CYAN(PASS), PR_data, memory[PAddr]);
        #1;
        @(posedge Clk);
        PR_req = 1'b0; // ack
        #1;

        /** Read miss
            Description: Should result in a cache miss at 0b101.
            Also maps to block 1, was in before but just got trashed.
        */
        $display("\n%s", `GREEN(Read request miss @ 0b101 (trashed block 1)));
        @(posedge Clk);
        PAddr = 8'b00000101;    // Fetch @0b00000101
        PR_req = 1'b1;          // Won't hit, should fetch from mem @ [4]
        #1;
        
        @(posedge MR_req);
        @(posedge Clk);
        $display("%s Memory read request @0b%b", `YELLOW(INFO), MAddr);
        MR_data = { memory[MAddr + 8'd3], memory[MAddr + 8'd2], memory[MAddr + 8'd1], memory[MAddr] };
        MR_rdy = 1'b1;
        #1;

        @(posedge PR_rdy);
        @(posedge Clk);
        MR_rdy = 1'b0;
        $display("%s Cache returned: 0b%b, should be: 0b%b.", `CYAN(PASS), PR_data, memory[PAddr]);
        #1;
        @(posedge Clk);
        PR_req = 1'b0; // ack
        #1;

        /** Write hit
            Description: Should result in a cache hit at 0b10.
            Should update both cache and memory with the value
            0b11111011 (0xfb).
        */
        $display("\n%s", `GREEN(Write request hit 0b11111011 => 0b10));
        @(posedge Clk);
        PAddr = 8'b00000010;
        PW_req = 1'b1;
        PW_data = 8'hfb;
        #1;

        @(posedge MW_req);
        @(posedge Clk);
        memory[MAddr] <= MW_data;
        MW_done <= 1'b1;
        #1;

        @(posedge PW_done);
        MW_done <= 1'b0;
        #1;
        @(posedge Clk);
        PW_req = 1'b0; // ack
        #1;

        @(posedge Clk);
        PAddr = 8'b00000010;    // Fetch @0b0000010 
        PR_req = 1'b1;          // should hit
        #1;

        @(posedge PR_rdy);
        $display("%s Following write hit. Memory has: 0b%b, Cache returned: 0b%b should be: 0b%b.", `CYAN(PASS), memory[PAddr], PR_data, PW_data);
        #1;
        @(posedge Clk);
        PR_req = 1'b0; // ack
        #1;

        /** Write miss
            Description: Should result in a cache miss at 0b100010 (34) => mblock8 => cblock0.
            Should update just memory with the value
            0b10101011 (0xab). Cache should still hit with block 0 values.
        */
        $display("\n%s", `GREEN(Write request miss 0b10101011 => 0b100010));
        @(posedge Clk);
        PAddr = 8'b00100010;
        PW_req = 1'b1;
        PW_data = 8'hab;
        #1;

        @(posedge MW_req);
        @(posedge Clk);
        memory[MAddr] <= MW_data;
        MW_done <= 1'b1;
        PW_req = 1'b0;
        #1;
        @(posedge Clk);
        #1; // Update cache

        @(posedge Clk);
        PAddr = 8'b00000010;    // Fetch @0b00000010
        PR_req = 1'b1;          // should hit
        #1;

        @(posedge PR_rdy);
        PR_req = 1'b0;
        $display("%s Cache returned: 0b%b, should be: 0b%b.", `CYAN(PASS), PR_data, memory[PAddr]); // From the hit write before
        $display("%s Following write miss, memory updated: 0b%b, should be 0b%b.", `CYAN(PASS), memory[8'b00100010], 8'hab);
        #1;
        @(posedge Clk);
        PR_req = 1'b0; // ack
        #1;

        @(posedge Clk) $finish;
    end

    always Clk = #1 ~Clk;
endmodule

computer_architecture/cache_verilog/Cache_tb.vcd
$date
	Sun Oct 03 11:27:42 2021
$end
$version
	Icarus Verilog
$end
$timescale
	1ns
$end
$scope module Cache_tb $end
$var wire 1 ! PW_done $end
$var wire 1 " PR_rdy $end
$var wire 8 # PR_data [7:0] $end
$var wire 1 $ MW_req $end
$var wire 8 % MW_data [7:0] $end
$var wire 1 & MR_req $end
$var wire 8 ' MAddr [7:0] $end
$var reg 1 ( Clk $end
$var reg 32 ) MR_data [31:0] $end
$var reg 1 * MR_rdy $end
$var reg 1 + MW_done $end
$var reg 8 , PAddr [7:0] $end
$var reg 1 - PR_req $end
$var reg 8 . PW_data [7:0] $end
$var reg 1 / PW_req $end
$var reg 1 0 Rst $end
$var integer 32 1 i [31:0] $end
$scope module dut $end
$var wire 32 2 MRead_data [31:0] $end
$var wire 1 * MRead_ready $end
$var wire 8 3 MWrite_data [7:0] $end
$var wire 1 + MWrite_done $end
$var wire 8 4 PAddress [7:0] $end
$var wire 8 5 PRead_data [7:0] $end
$var wire 1 - PRead_request $end
$var wire 8 6 PWrite_data [7:0] $end
$var wire 1 / PWrite_request $end
$var wire 1 ( clk $end
$var wire 1 0 rst $end
$var wire 3 7 tag [2:0] $end
$var wire 2 8 offset [1:0] $end
$var wire 3 9 block_index [2:0] $end
$var wire 1 ! PWrite_done $end
$var wire 1 " PRead_ready $end
$var wire 1 $ MWrite_request $end
$var wire 1 & MRead_request $end
$var wire 8 : MAddress [7:0] $end
$var reg 1 ; command $end
$var reg 1 < hit $end
$var reg 8 = read_buf [7:0] $end
$var reg 3 > state [2:0] $end
$var integer 32 ? i [31:0] $end
$var integer 32 @ j [31:0] $end
$upscope $end
$upscope $end
$enddefinitions $end
#0
$dumpvars
bx @
bx ?
bx >
bx =
x<
x;
b0 :
b0 9
b0 8
b0 7
b0 6
bx 5
b0 4
b0 3
b0 2
b1000000 1
10
0/
b0 .
0-
b0 ,
0+
0*
b0 )
0(
b0 '
x&
b0 %
x$
bx #
x"
x!
$end
#1
b0 #
b0 5
b0 =
0;
0&
0$
0"
0!
b0 >
b100 @
b1000 ?
1(
#2
0(
#3
b100 @
b1000 ?
1(
#4
0(
#5
00
1(
#6
0(
#7
1(
#8
0(
#9
1(
#10
0(
#11
1(
#12
0(
#13
1(
#14
0(
#15
b1 >
b1 9
b1 8
1-
b101 ,
b101 4
1(
#16
0(
#17
b100 '
b100 :
1&
b10 >
0<
1(
#18
0(
#19
b0 '
b0 :
0&
b11 >
1*
b111000001100000010100000100 )
b111000001100000010100000100 2
1(
#20
0(
#21
1"
b100 >
b101 #
b101 5
b101 =
1(
#22
0(
#23
0*
1(
#24
0(
#25
0"
b0 >
0-
1(
#26
0(
#27
b1 >
b0 9
b11 8
1-
b11 ,
b11 4
1(
#28
0(
#29
1&
b10 >
1(
#30
0(
#31
0&
b11 >
1*
b11000000100000000100000000 )
b11000000100000000100000000 2
1(
#32
0(
#33
1"
b100 >
b11 #
b11 5
b11 =
1(
#34
0(
#35
0*
1(
#36
0(
#37
0"
b0 >
0-
1(
#38
0(
#39
b1 >
b1 9
1-
b111 ,
b111 4
1(
#40
0(
#41
1"
b100 >
b111 #
b111 5
b111 =
1(
#42
0(
#43
1(
#44
0(
#45
0"
b0 >
0-
1(
#46
0(
#47
b1 >
b0 9
b1 8
1-
b1 ,
b1 4
1(
#48
0(
#49
1"
b100 >
b1 #
b1 5
b1 =
1(
#50
0(
#51
1(
#52
0(
#53
0"
b0 >
0-
1(
#54
0(
#55
b1 >
b1 7
b1 9
b10 8
1-
b100110 ,
b100110 4
1(
#56
0(
#57
b100100 '
b100100 :
1&
b10 >
1(
#58
0(
#59
b0 '
b0 :
0&
b11 >
1*
b100111001001100010010100100100 )
b100111001001100010010100100100 2
1(
#60
0(
#61
1"
b100 >
b100110 #
b100110 5
b100110 =
1(
#62
0(
#63
0*
1(
#64
0(
#65
0"
b0 >
0-
1(
#66
0(
#67
b1 >
b0 7
b1 8
1-
b101 ,
b101 4
1(
#68
0(
#69
b100 '
b100 :
1&
b10 >
1(
#70
0(
#71
b0 '
b0 :
0&
b11 >
1*
b111000001100000010100000100 )
b111000001100000010100000100 2
1(
#72
0(
#73
1"
b100 >
b101 #
b101 5
b101 =
1(
#74
0(
#75
0*
1(
#76
0(
#77
0"
b0 >
0-
1(
#78
0(
#79
b1 >
b0 9
b10 8
1;
b11111011 %
b11111011 3
b11111011 .
b11111011 6
1/
b10 ,
b10 4
1(
#80
0(
#81
b10 '
b10 :
1$
b101 >
1<
1(
#82
0(
#83
1+
1(
#84
0(
#85
b0 '
b0 :
0$
b110 >
1(
#86
0(
#87
0+
1!
b111 >
1(
#88
0(
#89
0!
b0 >
0/
1(
#90
0(
#91
b1 >
0;
1-
1(
#92
0(
#93
1"
b100 >
b11111011 #
b11111011 5
b11111011 =
1(
#94
0(
#95
0"
b0 >
0-
1(
#96
0(
#97
b1 >
b1 7
1;
b10101011 %
b10101011 3
b10101011 .
b10101011 6
1/
b100010 ,
b100010 4
1(
#98
0(
#99
b100010 '
b100010 :
1$
b101 >
0<
1(
#100
0(
#101
1+
0/
1(
#102
0(
#103
b0 '
b0 :
0$
b110 >
1(
#104
0(
#105
1!
b111 >
b0 7
1-
b10 ,
b10 4
1(
#106
0(
#107
0!
b0 >
1(
#108
0(
#109
b1 >
0;
1(
#110
0(
#111
0-
1"
b100 >
1(
#112
0(
#113
0"
b0 >
1(
